README.txt
setup.py
TracNukeUserPlugin.egg-info/PKG-INFO
TracNukeUserPlugin.egg-info/SOURCES.txt
TracNukeUserPlugin.egg-info/dependency_links.txt
TracNukeUserPlugin.egg-info/entry_points.txt
TracNukeUserPlugin.egg-info/requires.txt
TracNukeUserPlugin.egg-info/top_level.txt
nukeuserplugin/__init__.py