Metadata-Version: 1.0
Name: TracNukeUserPlugin
Version: 0.2.1
Summary: Removes the specified Trac user and all tickets they created
Home-page: https://github.com/slinkp/TracNukeUserPlugin
Author: Paul Winkler
Author-email: slinkp@gmail.com
License: BSD
Platform: UNKNOWN
Classifier: Development Status :: 4 - Beta
Classifier: Environment :: Console
Classifier: Framework :: Trac
Classifier: License :: OSI Approved :: BSD License
Classifier: Operating System :: OS Independent
Classifier: Programming Language :: Python :: 2
